{
    "$schema": "https://schema.management.azure.com/schemas/2015-01-01/deploymentTemplate.json#",
    "contentVersion": "1.0.0.0",
    "parameters": {
        "storageAccountName": {
            "type": "string"
        },
        "virtualNetworkName": {
            "type": "string"
        },
        "subnetName": {
            "type": "string"
        },
        "containerName": {
            "type": "string"
        },
        "accountSasProperties": {
            "type": "object",
            "defaultValue": {
                "signedServices": "b",
                "signedPermission": "rw",
                "signedExpiry": "2019-12-31T00:00:00Z",
                "signedResourceTypes": "o"
            }
        }
    },
    "variables": {
        "vnetId": "[resourceId(resourceGroup().name,'Microsoft.Network/virtualNetworks', parameters('virtualNetworkName'))]",
        "subnetRef": "[concat(variables('vnetId'), '/subnets/', parameters('subnetName'))]"
    },
    "resources": [
        {
            "type": "Microsoft.Storage/storageAccounts",
            "apiVersion": "2019-04-01",
            "name": "[parameters('storageAccountName')]",
            "location": "uksouth",
            "sku": {
                "name": "Standard_LRS",
                "tier": "Standard"
            },
            "kind": "StorageV2",
            "properties": {
                "networkAcls": {
                    "bypass": "AzureServices",
                    "virtualNetworkRules": [
                        {
                            "id": "[variables('subnetRef')]",
                            "action": "Allow",
                            "state": "Succeeded"
                        }
                    ],
                    "ipRules": [],
                    "defaultAction": "Deny"
                },
                "supportsHttpsTrafficOnly": true,
                "encryption": {
                    "services": {
                        "file": {
                            "enabled": true
                        },
                        "blob": {
                            "enabled": true
                        }
                    },
                    "keySource": "Microsoft.Storage"
                },
                "accessTier": "Cool"
            }
        },
        {
            "type": "Microsoft.Storage/storageAccounts/blobServices",
            "apiVersion": "2019-04-01",
            "name": "[concat(parameters('storageAccountName'), '/default')]",
            "dependsOn": [
                "[resourceId('Microsoft.Storage/storageAccounts', parameters('storageAccountName'))]"
            ],
            "properties": {
                "cors": {
                    "corsRules": []
                },
                "deleteRetentionPolicy": {
                    "enabled": false
                }
            }
        },
        {
            "type": "Microsoft.Storage/storageAccounts/blobServices/containers",
            "apiVersion": "2019-04-01",
            "name": "[concat(parameters('storageAccountName'), '/default/secrets')]",
            "dependsOn": [
                "[resourceId('Microsoft.Storage/storageAccounts/blobServices', parameters('storageAccountName'), 'default')]",
                "[resourceId('Microsoft.Storage/storageAccounts', parameters('storageAccountName'))]"
            ],
            "properties": {
                "publicAccess": "None"
            }
        }
    ],
    "outputs": {
        "_secretsLocation": {
            "type": "string",
            "value": "[concat('https://', parameters('storageAccountName'), '.blob.core.windows.net/', parameters('containerName'))]"
        },
        "_secretsLocationSasToken": {
            "type": "string",
            "value": "[concat('?', listAccountSas(parameters('storageAccountName'), '2018-07-01', parameters('accountSasProperties')).accountSasToken)]"
        }
    }
}
